fourier_comm_rs-0.0.10.dist-info/METADATA
fourier_comm_rs-0.0.10.dist-info/WHEEL
fourier_comm_rs/fourier_comm_rs.pyi
fourier_comm_rs/__init__.py
fourier_comm_rs/enums.py
fourier_comm_rs/py.typed
fourier_comm_rs/_internal.cpython-312-x86_64-linux-gnu.so
fourier_comm_rs-0.0.10.dist-info/RECORD
