Metadata-Version: 2.3
Name: fourier_comm_rs
Version: 0.0.10
Classifier: Development Status :: 3 - Alpha
Classifier: Intended Audience :: Developers
Classifier: License :: OSI Approved :: MIT License
Classifier: Programming Language :: Python :: 3
Classifier: Programming Language :: Rust
Classifier: Operating System :: OS Independent
Requires-Dist: cffi
Summary: A Rust library for communication with Fourier Motors and Encoders
Author: Yuxiang Gao <yuxiang.gao@fftai.com>
Author-email: Yuxiang Gao <yuxiang.gao@fftai.com>
License: MIT
